{
  "test_timestamp": "2025-07-27T02:03:38.749579",
  "scanners_tested": 5,
  "results": [
    {
      "scanner_id": "eth",
      "scanner_name": "Etherscan",
      "requires_api_key": true,
      "api_key_configured": true,
      "networks_tested": [
        "main",
        "sepolia"
      ],
      "total_methods": 44,
      "successful_methods": 31,
      "failed_methods": 13,
      "success_rate": 70.45454545454545,
      "method_results": {
        "proxy": [
          {
            "method_name": "block_number",
            "success": true,
            "error_type": null,
            "error_message": null,
            "execution_time": 0.41665101051330566
          },
          {
            "method_name": "get_balance",
            "success": true,
            "error_type": null,
            "error_message": null,
            "execution_time": 0.2201988697052002
          },
          {
            "method_name": "get_block_by_number",
            "success": true,
            "error_type": null,
            "error_message": null,
            "execution_time": 0.4423229694366455
          }
        ],
        "account": [
          {
            "method_name": "balance",
            "success": true,
            "error_type": null,
            "error_message": null,
            "execution_time": 0.21181321144104004
          },
          {
            "method_name": "normal_txs",
            "success": true,
            "error_type": null,
            "error_message": null,
            "execution_time": 0.2154541015625
          },
          {
            "method_name": "internal_txs",
            "success": true,
            "error_type": null,
            "error_message": null,
            "execution_time": 0.2156062126159668
          },
          {
            "method_name": "erc20_transfers",
            "success": true,
            "error_type": null,
            "error_message": null,
            "execution_time": 0.24828386306762695
          }
        ],
        "stats": [
          {
            "method_name": "eth_supply",
            "success": true,
            "error_type": null,
            "error_message": null,
            "execution_time": 0.21910500526428223
          },
          {
            "method_name": "eth_price",
            "success": true,
            "error_type": null,
            "error_message": null,
            "execution_time": 0.21433687210083008
          },
          {
            "method_name": "nodes_size",
            "success": false,
            "error_type": null,
            "error_message": null,
            "execution_time": 0.20885300636291504
          }
        ],
        "block": [
          {
            "method_name": "block_reward",
            "success": true,
            "error_type": null,
            "error_message": null,
            "execution_time": 0.21525788307189941
          },
          {
            "method_name": "block_countdown",
            "success": false,
            "error_type": "Exception",
            "error_message": "Past block for countdown",
            "execution_time": 0.21219992637634277
          },
          {
            "method_name": "daily_block_count",
            "success": false,
            "error_type": "API Error",
            "error_message": "[NOTOK] Error! Missing Or invalid Action name",
            "execution_time": 0.21061015129089355
          }
        ],
        "transaction": [
          {
            "method_name": "tx_receipt_status",
            "success": true,
            "error_type": null,
            "error_message": null,
            "execution_time": 0.22777819633483887
          },
          {
            "method_name": "check_tx_status",
            "success": true,
            "error_type": null,
            "error_message": null,
            "execution_time": 0.27712106704711914
          }
        ],
        "logs": [
          {
            "method_name": "get_logs",
            "success": false,
            "error_type": "API Error",
            "error_message": "[No records found] []",
            "execution_time": 0.2117302417755127
          }
        ],
        "gas_tracker": [
          {
            "method_name": "gas_estimate",
            "success": false,
            "error_type": "Feature Not Supported",
            "error_message": "Feature \"gas_estimate\" is not supported by eth:sepolia",
            "execution_time": 2.5033950805664062e-05
          },
          {
            "method_name": "gas_oracle",
            "success": false,
            "error_type": "API Error",
            "error_message": "[NOTOK] Error! Missing Or invalid Module name (#1)",
            "execution_time": 0.2184140682220459
          }
        ],
        "token": [
          {
            "method_name": "token_supply",
            "success": true,
            "error_type": null,
            "error_message": null,
            "execution_time": 0.20949006080627441
          },
          {
            "method_name": "token_balance",
            "success": true,
            "error_type": null,
            "error_message": null,
            "execution_time": 0.21648311614990234
          }
        ],
        "contract": [
          {
            "method_name": "contract_abi",
            "success": false,
            "error_type": "API Error",
            "error_message": "[NOTOK] Contract source code not verified",
            "execution_time": 0.21293115615844727
          },
          {
            "method_name": "contract_source",
            "success": false,
            "error_type": null,
            "error_message": null,
            "execution_time": 0.21135902404785156
          }
        ]
      },
      "errors": []
    },
    {
      "scanner_id": "bsc",
      "scanner_name": "BscScan",
      "requires_api_key": true,
      "api_key_configured": true,
      "networks_tested": [
        "main"
      ],
      "total_methods": 22,
      "successful_methods": 14,
      "failed_methods": 8,
      "success_rate": 63.63636363636363,
      "method_results": {
        "proxy": [
          {
            "method_name": "block_number",
            "success": true,
            "error_type": null,
            "error_message": null,
            "execution_time": 0.6321637630462646
          },
          {
            "method_name": "get_balance",
            "success": true,
            "error_type": null,
            "error_message": null,
            "execution_time": 0.16155195236206055
          },
          {
            "method_name": "get_block_by_number",
            "success": true,
            "error_type": null,
            "error_message": null,
            "execution_time": 0.2786710262298584
          }
        ],
        "account": [
          {
            "method_name": "balance",
            "success": true,
            "error_type": null,
            "error_message": null,
            "execution_time": 0.16171908378601074
          },
          {
            "method_name": "normal_txs",
            "success": true,
            "error_type": null,
            "error_message": null,
            "execution_time": 0.5617671012878418
          },
          {
            "method_name": "internal_txs",
            "success": true,
            "error_type": null,
            "error_message": null,
            "execution_time": 0.17388701438903809
          },
          {
            "method_name": "erc20_transfers",
            "success": true,
            "error_type": null,
            "error_message": null,
            "execution_time": 3.396782875061035
          }
        ],
        "stats": [
          {
            "method_name": "eth_supply",
            "success": false,
            "error_type": "API Error",
            "error_message": "[NOTOK] Error! Missing Or invalid Action name",
            "execution_time": 0.16525721549987793
          },
          {
            "method_name": "eth_price",
            "success": false,
            "error_type": "API Error",
            "error_message": "[NOTOK] Error! Missing Or invalid Action name",
            "execution_time": 0.16031599044799805
          },
          {
            "method_name": "nodes_size",
            "success": false,
            "error_type": null,
            "error_message": null,
            "execution_time": 0.16280674934387207
          }
        ],
        "block": [
          {
            "method_name": "block_reward",
            "success": true,
            "error_type": null,
            "error_message": null,
            "execution_time": 0.17103099822998047
          },
          {
            "method_name": "block_countdown",
            "success": false,
            "error_type": "Exception",
            "error_message": "Past block for countdown",
            "execution_time": 0.16243791580200195
          },
          {
            "method_name": "daily_block_count",
            "success": false,
            "error_type": "API Error",
            "error_message": "[NOTOK] Sorry, it looks like you are trying to access an API Pro endpoint. Contact us to upgrade to API Pro.",
            "execution_time": 0.16336512565612793
          }
        ],
        "transaction": [
          {
            "method_name": "tx_receipt_status",
            "success": true,
            "error_type": null,
            "error_message": null,
            "execution_time": 0.16107797622680664
          },
          {
            "method_name": "check_tx_status",
            "success": true,
            "error_type": null,
            "error_message": null,
            "execution_time": 0.1610853672027588
          }
        ],
        "logs": [
          {
            "method_name": "get_logs",
            "success": false,
            "error_type": "API Error",
            "error_message": "[No records found] []",
            "execution_time": 0.17287492752075195
          }
        ],
        "gas_tracker": [
          {
            "method_name": "gas_estimate",
            "success": false,
            "error_type": "Feature Not Supported",
            "error_message": "Feature \"gas_estimate\" is not supported by bsc:main",
            "execution_time": 1.4781951904296875e-05
          },
          {
            "method_name": "gas_oracle",
            "success": false,
            "error_type": "Feature Not Supported",
            "error_message": "Feature \"gas_oracle\" is not supported by bsc:main",
            "execution_time": 0.2132568359375
          }
        ],
        "token": [
          {
            "method_name": "token_supply",
            "success": true,
            "error_type": null,
            "error_message": null,
            "execution_time": 0.17343616485595703
          },
          {
            "method_name": "token_balance",
            "success": true,
            "error_type": null,
            "error_message": null,
            "execution_time": 0.1603701114654541
          }
        ],
        "contract": [
          {
            "method_name": "contract_abi",
            "success": true,
            "error_type": null,
            "error_message": null,
            "execution_time": 0.16646814346313477
          },
          {
            "method_name": "contract_source",
            "success": true,
            "error_type": null,
            "error_message": null,
            "execution_time": 0.16836023330688477
          }
        ]
      },
      "errors": []
    },
    {
      "scanner_id": "polygon",
      "scanner_name": "PolygonScan",
      "requires_api_key": true,
      "api_key_configured": true,
      "networks_tested": [
        "main"
      ],
      "total_methods": 22,
      "successful_methods": 16,
      "failed_methods": 6,
      "success_rate": 72.72727272727273,
      "method_results": {
        "proxy": [
          {
            "method_name": "block_number",
            "success": true,
            "error_type": null,
            "error_message": null,
            "execution_time": 0.6742479801177979
          },
          {
            "method_name": "get_balance",
            "success": true,
            "error_type": null,
            "error_message": null,
            "execution_time": 0.1594078540802002
          },
          {
            "method_name": "get_block_by_number",
            "success": true,
            "error_type": null,
            "error_message": null,
            "execution_time": 0.28600502014160156
          }
        ],
        "account": [
          {
            "method_name": "balance",
            "success": true,
            "error_type": null,
            "error_message": null,
            "execution_time": 0.15888190269470215
          },
          {
            "method_name": "normal_txs",
            "success": true,
            "error_type": null,
            "error_message": null,
            "execution_time": 0.2113049030303955
          },
          {
            "method_name": "internal_txs",
            "success": true,
            "error_type": null,
            "error_message": null,
            "execution_time": 0.16426897048950195
          },
          {
            "method_name": "erc20_transfers",
            "success": true,
            "error_type": null,
            "error_message": null,
            "execution_time": 0.28550219535827637
          }
        ],
        "stats": [
          {
            "method_name": "eth_supply",
            "success": true,
            "error_type": null,
            "error_message": null,
            "execution_time": 0.15999794006347656
          },
          {
            "method_name": "eth_price",
            "success": true,
            "error_type": null,
            "error_message": null,
            "execution_time": 0.16140985488891602
          },
          {
            "method_name": "nodes_size",
            "success": false,
            "error_type": null,
            "error_message": null,
            "execution_time": 0.15789389610290527
          }
        ],
        "block": [
          {
            "method_name": "block_reward",
            "success": true,
            "error_type": null,
            "error_message": null,
            "execution_time": 0.16109704971313477
          },
          {
            "method_name": "block_countdown",
            "success": false,
            "error_type": "Exception",
            "error_message": "Past block for countdown",
            "execution_time": 0.15868782997131348
          },
          {
            "method_name": "daily_block_count",
            "success": false,
            "error_type": "API Error",
            "error_message": "[NOTOK] Sorry, it looks like you are trying to access an API Pro endpoint. Contact us to upgrade to API Pro.",
            "execution_time": 0.19517207145690918
          }
        ],
        "transaction": [
          {
            "method_name": "tx_receipt_status",
            "success": true,
            "error_type": null,
            "error_message": null,
            "execution_time": 0.15935111045837402
          },
          {
            "method_name": "check_tx_status",
            "success": true,
            "error_type": null,
            "error_message": null,
            "execution_time": 0.16137409210205078
          }
        ],
        "logs": [
          {
            "method_name": "get_logs",
            "success": false,
            "error_type": "API Error",
            "error_message": "[No records found] []",
            "execution_time": 0.18988919258117676
          }
        ],
        "gas_tracker": [
          {
            "method_name": "gas_estimate",
            "success": false,
            "error_type": "Feature Not Supported",
            "error_message": "Feature \"gas_estimate\" is not supported by polygon:main",
            "execution_time": 5.91278076171875e-05
          },
          {
            "method_name": "gas_oracle",
            "success": false,
            "error_type": "Feature Not Supported",
            "error_message": "Feature \"gas_oracle\" is not supported by polygon:main",
            "execution_time": 0.2040691375732422
          }
        ],
        "token": [
          {
            "method_name": "token_supply",
            "success": true,
            "error_type": null,
            "error_message": null,
            "execution_time": 0.15979719161987305
          },
          {
            "method_name": "token_balance",
            "success": true,
            "error_type": null,
            "error_message": null,
            "execution_time": 0.15938115119934082
          }
        ],
        "contract": [
          {
            "method_name": "contract_abi",
            "success": true,
            "error_type": null,
            "error_message": null,
            "execution_time": 0.16701388359069824
          },
          {
            "method_name": "contract_source",
            "success": true,
            "error_type": null,
            "error_message": null,
            "execution_time": 0.27579712867736816
          }
        ]
      },
      "errors": []
    },
    {
      "scanner_id": "optimism",
      "scanner_name": "Optimism Etherscan",
      "requires_api_key": true,
      "api_key_configured": true,
      "networks_tested": [
        "main"
      ],
      "total_methods": 22,
      "successful_methods": 15,
      "failed_methods": 7,
      "success_rate": 68.18181818181817,
      "method_results": {
        "proxy": [
          {
            "method_name": "block_number",
            "success": true,
            "error_type": null,
            "error_message": null,
            "execution_time": 0.43351197242736816
          },
          {
            "method_name": "get_balance",
            "success": true,
            "error_type": null,
            "error_message": null,
            "execution_time": 0.21753883361816406
          },
          {
            "method_name": "get_block_by_number",
            "success": true,
            "error_type": null,
            "error_message": null,
            "execution_time": 0.323077917098999
          }
        ],
        "account": [
          {
            "method_name": "balance",
            "success": true,
            "error_type": null,
            "error_message": null,
            "execution_time": 0.21155214309692383
          },
          {
            "method_name": "normal_txs",
            "success": true,
            "error_type": null,
            "error_message": null,
            "execution_time": 0.24108123779296875
          },
          {
            "method_name": "internal_txs",
            "success": true,
            "error_type": null,
            "error_message": null,
            "execution_time": 0.43282389640808105
          },
          {
            "method_name": "erc20_transfers",
            "success": true,
            "error_type": null,
            "error_message": null,
            "execution_time": 0.23804402351379395
          }
        ],
        "stats": [
          {
            "method_name": "eth_supply",
            "success": false,
            "error_type": "Exception",
            "error_message": "Failed to perform, curl: (28) Operation timed out after 10001 milliseconds with 0 bytes received. See https://curl.se/libcurl/c/libcurl-errors.html first for more details.",
            "execution_time": 9.996678829193115
          },
          {
            "method_name": "eth_price",
            "success": true,
            "error_type": null,
            "error_message": null,
            "execution_time": 0.2220008373260498
          },
          {
            "method_name": "nodes_size",
            "success": false,
            "error_type": null,
            "error_message": null,
            "execution_time": 0.21247005462646484
          }
        ],
        "block": [
          {
            "method_name": "block_reward",
            "success": true,
            "error_type": null,
            "error_message": null,
            "execution_time": 0.21053385734558105
          },
          {
            "method_name": "block_countdown",
            "success": false,
            "error_type": "Exception",
            "error_message": "Past block for countdown",
            "execution_time": 0.21301722526550293
          },
          {
            "method_name": "daily_block_count",
            "success": false,
            "error_type": "API Error",
            "error_message": "[NOTOK] Sorry, it looks like you are trying to access an API Pro endpoint. Contact us to upgrade to API Pro.",
            "execution_time": 0.21811485290527344
          }
        ],
        "transaction": [
          {
            "method_name": "tx_receipt_status",
            "success": true,
            "error_type": null,
            "error_message": null,
            "execution_time": 0.21022605895996094
          },
          {
            "method_name": "check_tx_status",
            "success": true,
            "error_type": null,
            "error_message": null,
            "execution_time": 0.21127867698669434
          }
        ],
        "logs": [
          {
            "method_name": "get_logs",
            "success": false,
            "error_type": "API Error",
            "error_message": "[No records found] []",
            "execution_time": 0.21674704551696777
          }
        ],
        "gas_tracker": [
          {
            "method_name": "gas_estimate",
            "success": false,
            "error_type": "Feature Not Supported",
            "error_message": "Feature \"gas_estimate\" is not supported by optimism:main",
            "execution_time": 3.409385681152344e-05
          },
          {
            "method_name": "gas_oracle",
            "success": false,
            "error_type": "API Error",
            "error_message": "[NOTOK] Error! Missing Or invalid Module name (#1)",
            "execution_time": 0.21268892288208008
          }
        ],
        "token": [
          {
            "method_name": "token_supply",
            "success": true,
            "error_type": null,
            "error_message": null,
            "execution_time": 0.21682095527648926
          },
          {
            "method_name": "token_balance",
            "success": true,
            "error_type": null,
            "error_message": null,
            "execution_time": 0.21318507194519043
          }
        ],
        "contract": [
          {
            "method_name": "contract_abi",
            "success": true,
            "error_type": null,
            "error_message": null,
            "execution_time": 0.21179795265197754
          },
          {
            "method_name": "contract_source",
            "success": true,
            "error_type": null,
            "error_message": null,
            "execution_time": 0.21656394004821777
          }
        ]
      },
      "errors": []
    },
    {
      "scanner_id": "arbitrum",
      "scanner_name": "Arbiscan",
      "requires_api_key": true,
      "api_key_configured": true,
      "networks_tested": [
        "main"
      ],
      "total_methods": 22,
      "successful_methods": 16,
      "failed_methods": 6,
      "success_rate": 72.72727272727273,
      "method_results": {
        "proxy": [
          {
            "method_name": "block_number",
            "success": true,
            "error_type": null,
            "error_message": null,
            "execution_time": 1.3599998950958252
          },
          {
            "method_name": "get_balance",
            "success": true,
            "error_type": null,
            "error_message": null,
            "execution_time": 1.245964765548706
          },
          {
            "method_name": "get_block_by_number",
            "success": true,
            "error_type": null,
            "error_message": null,
            "execution_time": 0.20759296417236328
          }
        ],
        "account": [
          {
            "method_name": "balance",
            "success": true,
            "error_type": null,
            "error_message": null,
            "execution_time": 0.21646404266357422
          },
          {
            "method_name": "normal_txs",
            "success": true,
            "error_type": null,
            "error_message": null,
            "execution_time": 2.567082166671753
          },
          {
            "method_name": "internal_txs",
            "success": true,
            "error_type": null,
            "error_message": null,
            "execution_time": 0.7541000843048096
          },
          {
            "method_name": "erc20_transfers",
            "success": true,
            "error_type": null,
            "error_message": null,
            "execution_time": 0.28191614151000977
          }
        ],
        "stats": [
          {
            "method_name": "eth_supply",
            "success": true,
            "error_type": null,
            "error_message": null,
            "execution_time": 0.5307700634002686
          },
          {
            "method_name": "eth_price",
            "success": true,
            "error_type": null,
            "error_message": null,
            "execution_time": 0.20488762855529785
          },
          {
            "method_name": "nodes_size",
            "success": false,
            "error_type": null,
            "error_message": null,
            "execution_time": 0.205369234085083
          }
        ],
        "block": [
          {
            "method_name": "block_reward",
            "success": true,
            "error_type": null,
            "error_message": null,
            "execution_time": 0.20565104484558105
          },
          {
            "method_name": "block_countdown",
            "success": false,
            "error_type": "Exception",
            "error_message": "Past block for countdown",
            "execution_time": 0.2020890712738037
          },
          {
            "method_name": "daily_block_count",
            "success": false,
            "error_type": "API Error",
            "error_message": "[NOTOK] Sorry, it looks like you are trying to access an API Pro endpoint. Contact us to upgrade to API Pro.",
            "execution_time": 0.2044508457183838
          }
        ],
        "transaction": [
          {
            "method_name": "tx_receipt_status",
            "success": true,
            "error_type": null,
            "error_message": null,
            "execution_time": 0.2036299705505371
          },
          {
            "method_name": "check_tx_status",
            "success": true,
            "error_type": null,
            "error_message": null,
            "execution_time": 0.20378327369689941
          }
        ],
        "logs": [
          {
            "method_name": "get_logs",
            "success": false,
            "error_type": "API Error",
            "error_message": "[No records found] []",
            "execution_time": 0.8515551090240479
          }
        ],
        "gas_tracker": [
          {
            "method_name": "gas_estimate",
            "success": false,
            "error_type": "Feature Not Supported",
            "error_message": "Feature \"gas_estimate\" is not supported by arbitrum:main",
            "execution_time": 2.0265579223632812e-05
          },
          {
            "method_name": "gas_oracle",
            "success": false,
            "error_type": "API Error",
            "error_message": "[NOTOK] Error! Missing Or invalid Module name (#1)",
            "execution_time": 0.2047269344329834
          }
        ],
        "token": [
          {
            "method_name": "token_supply",
            "success": true,
            "error_type": null,
            "error_message": null,
            "execution_time": 0.20627379417419434
          },
          {
            "method_name": "token_balance",
            "success": true,
            "error_type": null,
            "error_message": null,
            "execution_time": 0.20886588096618652
          }
        ],
        "contract": [
          {
            "method_name": "contract_abi",
            "success": true,
            "error_type": null,
            "error_message": null,
            "execution_time": 0.2064039707183838
          },
          {
            "method_name": "contract_source",
            "success": true,
            "error_type": null,
            "error_message": null,
            "execution_time": 0.3185410499572754
          }
        ]
      },
      "errors": []
    }
  ]
}